mycliapp/__init__.py
mycliapp/main.py
mycliapp12-0.1.dist-info/METADATA
mycliapp12-0.1.dist-info/WHEEL
mycliapp12-0.1.dist-info/entry_points.txt
mycliapp12-0.1.dist-info/top_level.txt
mycliapp12-0.1.dist-info/RECORD
