Metadata-Version: 2.1
Name: mycliapp12
Version: 0.1
Summary: UNKNOWN
Home-page: UNKNOWN
License: UNKNOWN
Platform: UNKNOWN
Requires-Dist: click
Requires-Dist: databricks-sql-connector
